gauge_nn_interpretability/__init__.py
gauge_nn_interpretability/cli.py
gauge_nn_interpretability/gauge_operators.py
gauge_nn_interpretability/transformer_analyzer.py
gauge_nn_interpretability/visualizer.py
gauge_nn_interpretability-1.0.3.dist-info/licenses/LICENSE
gauge_nn_interpretability-1.0.3.dist-info/METADATA
gauge_nn_interpretability-1.0.3.dist-info/WHEEL
gauge_nn_interpretability-1.0.3.dist-info/entry_points.txt
gauge_nn_interpretability-1.0.3.dist-info/top_level.txt
gauge_nn_interpretability-1.0.3.dist-info/RECORD
