Metadata-Version: 2.4
Name: gauge-nn-interpretability
Version: 1.0.3
Summary: Computational Gauge Theory for Neural Network Interpretability
Home-page: https://github.com/theaicowboys/gauge-nn-interpretability
Author: Michael J. Pendleton
Author-email: michael.pendleton.20@gmail.com
Project-URL: Bug Reports, https://github.com/theaicowboys/gauge-nn-interpretability/issues
Project-URL: Source, https://github.com/theaicowboys/gauge-nn-interpretability
Project-URL: Documentation, https://github.com/theaicowboys/gauge-nn-interpretability/docs
Keywords: neural-networks interpretability gauge-theory transformers machine-learning
Classifier: Development Status :: 4 - Beta
Classifier: Intended Audience :: Science/Research
Classifier: Intended Audience :: Developers
Classifier: Topic :: Scientific/Engineering :: Artificial Intelligence
Classifier: Topic :: Scientific/Engineering :: Mathematics
Classifier: Programming Language :: Python :: 3
Classifier: Programming Language :: Python :: 3.8
Classifier: Programming Language :: Python :: 3.9
Classifier: Programming Language :: Python :: 3.10
Classifier: Programming Language :: Python :: 3.11
Classifier: Programming Language :: Python :: 3.12
Requires-Python: >=3.8
License-File: LICENSE
Requires-Dist: torch>=2.0.0
Requires-Dist: transformers>=4.30.0
Requires-Dist: numpy>=1.24.0
Requires-Dist: matplotlib>=3.7.0
Requires-Dist: seaborn>=0.12.0
Requires-Dist: scipy>=1.10.0
Requires-Dist: tqdm>=4.65.0
Dynamic: author
Dynamic: author-email
Dynamic: classifier
Dynamic: description
Dynamic: description-content-type
Dynamic: home-page
Dynamic: keywords
Dynamic: license-file
Dynamic: project-url
Dynamic: requires-dist
Dynamic: requires-python
Dynamic: summary
